django_politico_staff-0.0.15.dist-info/METADATA
django_politico_staff-0.0.15.dist-info/RECORD
django_politico_staff-0.0.15.dist-info/WHEEL
django_politico_staff-0.0.15.dist-info/top_level.txt
staff/__init__.py
staff/admin.py
staff/apps.py
staff/celery.py
staff/conf.py
staff/signals.py
staff/urls.py
staff/management/__init__.py
staff/management/commands/__init__.py
staff/management/commands/sync_slack_users.py
staff/migrations/0001_initial.py
staff/migrations/__init__.py
staff/models/__init__.py
staff/models/profile.py
staff/serializers/__init__.py
staff/serializers/profile.py
staff/serializers/user.py
staff/static/staff/css/main.edit.css
staff/static/staff/js/main.edit.js
staff/tasks/__init__.py
staff/tasks/user.py
staff/templates/staff/edit.html
staff/utils/__init__.py
staff/utils/auth.py
staff/utils/importers.py
staff/views/__init__.py
staff/views/edit.py
staff/views/sync.py
staff/viewsets/__init__.py
staff/viewsets/staffer.py
